models/__init__.py
models/availability.py
models/availability_request.py
models/availability_series.py
models/group.py
models/group_admins_link.py
models/group_members_link.py
models/models.py
models/repeating_availability.py
models/user.py
sts_models_tj-0.0.65.dist-info/METADATA
sts_models_tj-0.0.65.dist-info/WHEEL
sts_models_tj-0.0.65.dist-info/top_level.txt
sts_models_tj-0.0.65.dist-info/RECORD
