Metadata-Version: 2.1
Name: sts-models-tj
Version: 0.0.65
Summary: models for sts
Home-page: https://github.com/tbindseil/sts-mono-repo
Author: tj
Author-email: tjbindseil@gmail.com
License: UNKNOWN
Platform: UNKNOWN
Classifier: Programming Language :: Python :: 3
Classifier: License :: OSI Approved :: MIT License
Classifier: Operating System :: OS Independent
Requires-Python: >=3.6
Requires-Dist: sqlalchemy
